system_initiative_api_client/__init__.py
system_initiative_api_client/api_client.py
system_initiative_api_client/api_response.py
system_initiative_api_client/configuration.py
system_initiative_api_client/exceptions.py
system_initiative_api_client/py.typed
system_initiative_api_client/rest.py
system_initiative_api_client/api/__init__.py
system_initiative_api_client/api/actions_api.py
system_initiative_api_client/api/change_sets_api.py
system_initiative_api_client/api/components_api.py
system_initiative_api_client/api/debug_funcs_api.py
system_initiative_api_client/api/funcs_api.py
system_initiative_api_client/api/management_funcs_api.py
system_initiative_api_client/api/root_api.py
system_initiative_api_client/api/schemas_api.py
system_initiative_api_client/api/search_api.py
system_initiative_api_client/api/secrets_api.py
system_initiative_api_client/api/whoami_api.py
system_initiative_api_client/api/workspace_management_api.py
system_initiative_api_client/models/__init__.py
system_initiative_api_client/models/action_reference.py
system_initiative_api_client/models/action_reference_one_of.py
system_initiative_api_client/models/action_reference_one_of1.py
system_initiative_api_client/models/action_v1_request_path.py
system_initiative_api_client/models/action_view_v1.py
system_initiative_api_client/models/add_action_v1_request.py
system_initiative_api_client/models/add_action_v1_response.py
system_initiative_api_client/models/add_to_view_v1_request.py
system_initiative_api_client/models/api_error.py
system_initiative_api_client/models/api_success_string.py
system_initiative_api_client/models/attribute_argument_binding_request.py
system_initiative_api_client/models/building_response_v1.py
system_initiative_api_client/models/cancel_action_v1_response.py
system_initiative_api_client/models/change_set_view_v1.py
system_initiative_api_client/models/component_details_v1.py
system_initiative_api_client/models/component_prop_key.py
system_initiative_api_client-1.12.0.dist-info/licenses/LICENSE
system_initiative_api_client-1.12.0.dist-info/METADATA
system_initiative_api_client-1.12.0.dist-info/WHEEL
system_initiative_api_client-1.12.0.dist-info/top_level.txt
system_initiative_api_client-1.12.0.dist-info/RECORD
