Metadata-Version: 2.4
Name: system_initiative_api_client
Version: 1.12.0
Summary: Python SDK for the System Initiative Public API
Home-page: https://github.com/systeminit/si
Author: System Initiative
Author-email: System Initiative <support@systeminit.com>
License-Expression: Apache-2.0
Project-URL: Homepage, https://github.com/systeminit/si
Project-URL: Bug Tracker, https://github.com/systeminit/si/issues
Project-URL: Documentation, https://docs.systeminit.com/reference/public-api
Project-URL: Source Code, https://github.com/systeminit/si
Classifier: Development Status :: 5 - Production/Stable
Classifier: Intended Audience :: Developers
Classifier: Programming Language :: Python :: 3
Classifier: Programming Language :: Python :: 3.8
Classifier: Programming Language :: Python :: 3.9
Classifier: Programming Language :: Python :: 3.10
Classifier: Programming Language :: Python :: 3.11
Classifier: Operating System :: OS Independent
Requires-Python: >= 3.8
License-File: LICENSE
Requires-Dist: urllib3<3.0.0,>=2.1.0
Requires-Dist: python-dateutil>=2.8.2
Requires-Dist: pydantic>=2
Requires-Dist: typing-extensions>=4.7.1
Dynamic: author
Dynamic: home-page
Dynamic: license-file
Dynamic: requires-python
